[
  {
    "id": "demo-route",
    "title": "Демо-маршрут по парку",
    "description": "Прогулка по центральному парку с 4 остановками. Протяжённость ~1.5 км, около 40 минут.",
    "coverImage": "/maps/demo-route.svg",
    "mapImage": "/maps/demo-route.svg",
    "mapDimensions": { "width": 1200, "height": 800 },
    "distance": 1500,
    "duration": 40,
    "calibration": [
      { "gps": { "lat": 55.7558, "lng": 37.6173 }, "pixel": { "x": 100, "y": 150 } },
      { "gps": { "lat": 55.7600, "lng": 37.6250 }, "pixel": { "x": 900, "y": 100 } },
      { "gps": { "lat": 55.7520, "lng": 37.6220 }, "pixel": { "x": 700, "y": 650 } }
    ],
    "routePath": [
      { "x": 150, "y": 200 },
      { "x": 250, "y": 170 },
      { "x": 350, "y": 190 },
      { "x": 450, "y": 280 },
      { "x": 500, "y": 350 },
      { "x": 560, "y": 380 },
      { "x": 630, "y": 390 },
      { "x": 700, "y": 400 },
      { "x": 780, "y": 370 },
      { "x": 850, "y": 330 },
      { "x": 900, "y": 300 }
    ],
    "stops": [
      {
        "id": "stop-1",
        "title": "Вход в парк",
        "description": "Главный вход с фонтаном. Здесь начинается наша прогулка по старинному парку, заложенному в XIX веке.",
        "position": { "x": 150, "y": 200 },
        "photo": "",
        "audio": "",
        "order": 0
      },
      {
        "id": "stop-2",
        "title": "Озеро",
        "description": "Живописное озеро с утками. Летом здесь можно покормить уток и полюбоваться кувшинками.",
        "position": { "x": 500, "y": 350 },
        "photo": "",
        "audio": "",
        "order": 1
      },
      {
        "id": "stop-3",
        "title": "Смотровая площадка",
        "description": "Лучший вид на закат. С этой точки открывается панорама на весь парк и окрестности.",
        "position": { "x": 700, "y": 400 },
        "photo": "",
        "audio": "",
        "order": 2
      },
      {
        "id": "stop-4",
        "title": "Выход",
        "description": "Южный выход из парка. Рядом — кафе и остановка общественного транспорта.",
        "position": { "x": 900, "y": 300 },
        "photo": "",
        "audio": "",
        "order": 3
      }
    ]
  }
]
